{"cameraMode":{"drawMode":0,"name":"Shaded","section":"Shading Mode"},"sceneLighting":false,"audioPlay":false,"sceneViewState":{"showFog":true,"showMaterialUpdate":false,"showSkybox":false,"showFlares":true,"showImageEffects":true,"showParticleSystems":true},"in2DMode":false,"pivot":{"x":-4.045432433485985e-9,"y":0.0,"z":2.444721758365631e-9},"rotation":{"x":0.7205817103385925,"y":-0.001907397760078311,"z":0.0018993229605257512,"w":0.6934286952018738},"size":0.3042261004447937,"orthographic":false}